odoo/addons/l10n_ro_hr_medical_holidays/README.rst
odoo/addons/l10n_ro_hr_medical_holidays/__init__.py
odoo/addons/l10n_ro_hr_medical_holidays/__manifest__.py
odoo/addons/l10n_ro_hr_medical_holidays/demo/demo.xml
odoo/addons/l10n_ro_hr_medical_holidays/i18n/l10n_ro_hr_medical_holidays.pot
odoo/addons/l10n_ro_hr_medical_holidays/models/__init__.py
odoo/addons/l10n_ro_hr_medical_holidays/models/hr_holidays.py
odoo/addons/l10n_ro_hr_medical_holidays/security/ir.model.access.csv
odoo/addons/l10n_ro_hr_medical_holidays/static/description/icon.png
odoo/addons/l10n_ro_hr_medical_holidays/tests/__init__.py
odoo/addons/l10n_ro_hr_medical_holidays/tests/test_medical_holidays.py
odoo/addons/l10n_ro_hr_medical_holidays/views/hr_holidays_view.xml
odoo11_addon_l10n_ro_hr_medical_holidays-11.0.1.0.0.99.dev5.dist-info/METADATA
odoo11_addon_l10n_ro_hr_medical_holidays-11.0.1.0.0.99.dev5.dist-info/WHEEL
odoo11_addon_l10n_ro_hr_medical_holidays-11.0.1.0.0.99.dev5.dist-info/top_level.txt
odoo11_addon_l10n_ro_hr_medical_holidays-11.0.1.0.0.99.dev5.dist-info/RECORD
