Metadata-Version: 2.1
Name: odoo11-addon-l10n-ro-hr-medical-holidays
Version: 11.0.1.0.0.99.dev5
Summary: Romania - Medical Leaves
Home-page: https://github.com/OCA/l10n-romania
Author: NextERP Romania,Forest and Biomass Romania,Odoo Community Association (OCA)
Author-email: support@odoo-community.org
License: AGPL-3
Platform: UNKNOWN
Classifier: Programming Language :: Python
Classifier: Framework :: Odoo
Classifier: License :: OSI Approved :: GNU Affero General Public License v3
Classifier: Development Status :: 6 - Mature
Requires-Python: >=2.7, !=3.0.*, !=3.1.*, !=3.2.*, !=3.3.*, !=3.4.*
Requires-Dist: odoo11-addon-hr-holidays-public
Requires-Dist: odoo11-addon-l10n-ro-hr
Requires-Dist: odoo (<11.1dev,>=11.0a)
